{
  "sourceInterfaceId": "willibald.webshop.bestellung",
  "sourceSystemId": "willibald.webshop",
  "schema": "webshop",
  "catalog": "Willibald",
  "name": "bestellung",
  "sourceAttributes": [
    {
      "name": "bestellungid",
      "isPk": true,
      "isFk": false,
      "attributeProperties": {
        "position": 1,
        "default": null,
        "nullable": false,
        "datatype": "BIGINT",
        "length": 0
      }
    },
    {
      "name": "kundeid",
      "isPk": false,
      "isFk": false,
      "attributeProperties": {
        "position": 2,
        "default": null,
        "nullable": false,
        "datatype": "CHAR",
        "length": 13
      }
    },
    {
      "name": "allglieferadrid",
      "isPk": false,
      "isFk": false,
      "attributeProperties": {
        "position": 3,
        "default": null,
        "nullable": false,
        "datatype": "INT",
        "length": 0
      }
    },
    {
      "name": "bestelldatum",
      "isPk": false,
      "isFk": false,
      "attributeProperties": {
        "position": 4,
        "default": null,
        "nullable": false,
        "datatype": "DATE",
        "length": 0
      }
    },
    {
      "name": "wunschdatum",
      "isPk": false,
      "isFk": false,
      "attributeProperties": {
        "position": 5,
        "default": null,
        "nullable": false,
        "datatype": "DATE",
        "length": 0
      }
    },
    {
      "name": "rabatt",
      "isPk": false,
      "isFk": false,
      "attributeProperties": {
        "position": 6,
        "default": null,
        "nullable": false,
        "datatype": "NUMERIC",
        "length": 5,
        "precision": 2
      }
    }
  ],
  "sourceAttributeRelations": []
}